pangeo_forge_earthdatalogin/__init__.py
pangeo_forge_earthdatalogin/_version.py
pangeo_forge_earthdatalogin-0.2.dist-info/LICENSE
pangeo_forge_earthdatalogin-0.2.dist-info/METADATA
pangeo_forge_earthdatalogin-0.2.dist-info/WHEEL
pangeo_forge_earthdatalogin-0.2.dist-info/top_level.txt
pangeo_forge_earthdatalogin-0.2.dist-info/RECORD
